{"traceEvents": [{"name": "Kernel", "ph": "B", "ts": 1153739.84, "pid": 0, "tid": 142, "args": {"cta": 0}}, {"name": "Kernel", "ph": "B", "ts": 1153739.776, "pid": 0, "tid": 143, "args": {"cta": 1}}, {"name": "Kernel", "ph": "B", "ts": 1153739.872, "pid": 0, "tid": 144, "args": {"cta": 2}}, {"name": "Kernel", "ph": "B", "ts": 1153739.904, "pid": 0, "tid": 145, "args": {"cta": 3}}, {"name": "Kernel", "ph": "B", "ts": 1153739.776, "pid": 0, "tid": 146, "args": {"cta": 4}}, {"name": "Kernel", "ph": "B", "ts": 1153739.776, "pid": 0, "tid": 147, "args": {"cta": 5}}, {"name": "Kernel", "ph": "B", "ts": 1153739.744, "pid": 0, "tid": 0, "args": {"cta": 6}}, {"name": "Kernel", "ph": "B", "ts": 1153739.744, "pid": 0, "tid": 1, "args": {"cta": 7}}, {"name": "Kernel", "ph": "B", "ts": 1153739.904, "pid": 0, "tid": 2, "args": {"cta": 8}}, {"name": "Kernel", "ph": "B", "ts": 1153739.872, "pid": 0, "tid": 3, "args": {"cta": 9}}, {"name": "Kernel", "ph": "B", "ts": 1153739.872, "pid": 0, "tid": 4, "args": {"cta": 10}}, {"name": "Kernel", "ph": "B", "ts": 1153739.872, "pid": 0, "tid": 5, "args": {"cta": 11}}, {"name": "Kernel", "ph": "B", "ts": 1153739.872, "pid": 0, "tid": 6, "args": {"cta": 12}}, {"name": "Kernel", "ph": "B", "ts": 1153739.904, "pid": 0, "tid": 7, "args": {"cta": 13}}, {"name": "Kernel", "ph": "B", "ts": 1153739.872, "pid": 0, "tid": 8, "args": {"cta": 14}}, {"name": "Kernel", "ph": "B", "ts": 1153739.872, "pid": 0, "tid": 9, "args": {"cta": 15}}, {"name": "Kernel", "ph": "B", "ts": 1153739.744, "pid": 0, "tid": 10, "args": {"cta": 16}}, {"name": "Kernel", "ph": "B", "ts": 1153739.744, "pid": 0, "tid": 11, "args": {"cta": 17}}, {"name": "Kernel", "ph": "B", "ts": 1153739.776, "pid": 0, "tid": 12, "args": {"cta": 18}}, {"name": "Kernel", "ph": "B", "ts": 1153739.776, "pid": 0, "tid": 13, "args": {"cta": 19}}, {"name": "Kernel", "ph": "B", "ts": 1153739.776, "pid": 0, "tid": 14, "args": {"cta": 20}}, {"name": "Kernel", "ph": "B", "ts": 1153739.776, "pid": 0, "tid": 15, "args": {"cta": 21}}, {"name": "Kernel", "ph": "B", "ts": 1153739.744, "pid": 0, "tid": 16, "args": {"cta": 22}}, {"name": "Kernel", "ph": "B", "ts": 1153739.744, "pid": 0, "tid": 17, "args": {"cta": 23}}, {"name": "Kernel", "ph": "B", "ts": 1153739.904, "pid": 0, "tid": 18, "args": {"cta": 24}}, {"name": "Kernel", "ph": "B", "ts": 1153739.904, "pid": 0, "tid": 19, "args": {"cta": 25}}, {"name": "Kernel", "ph": "B", "ts": 1153739.904, "pid": 0, "tid": 20, "args": {"cta": 26}}, {"name": "Kernel", "ph": "B", "ts": 1153739.904, "pid": 0, "tid": 21, "args": {"cta": 27}}, {"name": "Kernel", "ph": "B", "ts": 1153739.904, "pid": 0, "tid": 22, "args": {"cta": 28}}, {"name": "Kernel", "ph": "B", "ts": 1153739.904, "pid": 0, "tid": 23, "args": {"cta": 29}}, {"name": "Kernel", "ph": "B", "ts": 1153739.872, "pid": 0, "tid": 24, "args": {"cta": 30}}, {"name": "Kernel", "ph": "B", "ts": 1153739.904, "pid": 0, "tid": 25, "args": {"cta": 31}}, {"name": "Kernel", "ph": "B", "ts": 1153739.776, "pid": 0, "tid": 26, "args": {"cta": 32}}, {"name": "Kernel", "ph": "B", "ts": 1153739.776, "pid": 0, "tid": 27, "args": {"cta": 33}}, {"name": "Kernel", "ph": "B", "ts": 1153739.808, "pid": 0, "tid": 28, "args": {"cta": 34}}, {"name": "Kernel", "ph": "B", "ts": 1153739.776, "pid": 0, "tid": 29, "args": {"cta": 35}}, {"name": "Kernel", "ph": "B", "ts": 1153739.808, "pid": 0, "tid": 30, "args": {"cta": 36}}, {"name": "Kernel", "ph": "B", "ts": 1153739.776, "pid": 0, "tid": 31, "args": {"cta": 37}}, {"name": "Kernel", "ph": "B", "ts": 1153739.744, "pid": 0, "tid": 32, "args": {"cta": 38}}, {"name": "Kernel", "ph": "B", "ts": 1153739.776, "pid": 0, "tid": 33, "args": {"cta": 39}}, {"name": "Kernel", "ph": "B", "ts": 1153739.904, "pid": 0, "tid": 34, "args": {"cta": 40}}, {"name": "Kernel", "ph": "B", "ts": 1153739.904, "pid": 0, "tid": 35, "args": {"cta": 41}}, {"name": "Kernel", "ph": "B", "ts": 1153739.904, "pid": 0, "tid": 36, "args": {"cta": 42}}, {"name": "Kernel", "ph": "B", "ts": 1153739.904, "pid": 0, "tid": 37, "args": {"cta": 43}}, {"name": "Kernel", "ph": "B", "ts": 1153739.904, "pid": 0, "tid": 38, "args": {"cta": 44}}, {"name": "Kernel", "ph": "B", "ts": 1153739.904, "pid": 0, "tid": 39, "args": {"cta": 45}}, {"name": "Kernel", "ph": "B", "ts": 1153739.872, "pid": 0, "tid": 40, "args": {"cta": 46}}, {"name": "Kernel", "ph": "B", "ts": 1153739.904, "pid": 0, "tid": 41, "args": {"cta": 47}}, {"name": "Kernel", "ph": "B", "ts": 1153739.776, "pid": 0, "tid": 42, "args": {"cta": 48}}, {"name": "Kernel", "ph": "B", "ts": 1153739.776, "pid": 0, "tid": 43, "args": {"cta": 49}}, {"name": "Kernel", "ph": "B", "ts": 1153739.808, "pid": 0, "tid": 44, "args": {"cta": 50}}, {"name": "Kernel", "ph": "B", "ts": 1153739.776, "pid": 0, "tid": 45, "args": {"cta": 51}}, {"name": "Kernel", "ph": "B", "ts": 1153739.776, "pid": 0, "tid": 46, "args": {"cta": 52}}, {"name": "Kernel", "ph": "B", "ts": 1153739.776, "pid": 0, "tid": 47, "args": {"cta": 53}}, {"name": "Kernel", "ph": "B", "ts": 1153739.776, "pid": 0, "tid": 48, "args": {"cta": 54}}, {"name": "Kernel", "ph": "B", "ts": 1153739.776, "pid": 0, "tid": 49, "args": {"cta": 55}}, {"name": "Kernel", "ph": "B", "ts": 1153739.904, "pid": 0, "tid": 50, "args": {"cta": 56}}, {"name": "Kernel", "ph": "B", "ts": 1153739.936, "pid": 0, "tid": 51, "args": {"cta": 57}}, {"name": "Kernel", "ph": "B", "ts": 1153739.936, "pid": 0, "tid": 52, "args": {"cta": 58}}, {"name": "Kernel", "ph": "B", "ts": 1153739.936, "pid": 0, "tid": 53, "args": {"cta": 59}}, {"name": "Kernel", "ph": "B", "ts": 1153739.936, "pid": 0, "tid": 54, "args": {"cta": 60}}, {"name": "Kernel", "ph": "B", "ts": 1153739.936, "pid": 0, "tid": 55, "args": {"cta": 61}}, {"name": "Kernel", "ph": "B", "ts": 1153739.904, "pid": 0, "tid": 56, "args": {"cta": 62}}, {"name": "Kernel", "ph": "B", "ts": 1153739.904, "pid": 0, "tid": 57, "args": {"cta": 63}}, {"name": "Kernel", "ph": "B", "ts": 1153739.808, "pid": 0, "tid": 58, "args": {"cta": 64}}, {"name": "Kernel", "ph": "B", "ts": 1153739.808, "pid": 0, "tid": 59, "args": {"cta": 65}}, {"name": "Kernel", "ph": "B", "ts": 1153739.84, "pid": 0, "tid": 60, "args": {"cta": 66}}, {"name": "Kernel", "ph": "B", "ts": 1153739.84, "pid": 0, "tid": 61, "args": {"cta": 67}}, {"name": "Kernel", "ph": "B", "ts": 1153739.84, "pid": 0, "tid": 62, "args": {"cta": 68}}, {"name": "Kernel", "ph": "B", "ts": 1153739.808, "pid": 0, "tid": 63, "args": {"cta": 69}}, {"name": "Kernel", "ph": "B", "ts": 1153739.776, "pid": 0, "tid": 64, "args": {"cta": 70}}, {"name": "Kernel", "ph": "B", "ts": 1153739.776, "pid": 0, "tid": 65, "args": {"cta": 71}}, {"name": "Kernel", "ph": "B", "ts": 1153739.872, "pid": 0, "tid": 66, "args": {"cta": 72}}, {"name": "Kernel", "ph": "B", "ts": 1153739.872, "pid": 0, "tid": 67, "args": {"cta": 73}}, {"name": "Kernel", "ph": "B", "ts": 1153739.872, "pid": 0, "tid": 68, "args": {"cta": 74}}, {"name": "Kernel", "ph": "B", "ts": 1153739.872, "pid": 0, "tid": 69, "args": {"cta": 75}}, {"name": "Kernel", "ph": "B", "ts": 1153739.872, "pid": 0, "tid": 70, "args": {"cta": 76}}, {"name": "Kernel", "ph": "B", "ts": 1153739.904, "pid": 0, "tid": 71, "args": {"cta": 77}}, {"name": "Kernel", "ph": "B", "ts": 1153739.872, "pid": 0, "tid": 72, "args": {"cta": 78}}, {"name": "Kernel", "ph": "B", "ts": 1153739.872, "pid": 0, "tid": 73, "args": {"cta": 79}}, {"name": "Kernel", "ph": "B", "ts": 1153739.776, "pid": 0, "tid": 74, "args": {"cta": 80}}, {"name": "Kernel", "ph": "B", "ts": 1153739.776, "pid": 0, "tid": 75, "args": {"cta": 81}}, {"name": "Kernel", "ph": "B", "ts": 1153739.776, "pid": 0, "tid": 76, "args": {"cta": 82}}, {"name": "Kernel", "ph": "B", "ts": 1153739.776, "pid": 0, "tid": 77, "args": {"cta": 83}}, {"name": "Kernel", "ph": "B", "ts": 1153739.776, "pid": 0, "tid": 78, "args": {"cta": 84}}, {"name": "Kernel", "ph": "B", "ts": 1153739.776, "pid": 0, "tid": 79, "args": {"cta": 85}}, {"name": "Kernel", "ph": "B", "ts": 1153739.904, "pid": 0, "tid": 80, "args": {"cta": 86}}, {"name": "Kernel", "ph": "B", "ts": 1153739.904, "pid": 0, "tid": 81, "args": {"cta": 87}}, {"name": "Kernel", "ph": "B", "ts": 1153739.936, "pid": 0, "tid": 82, "args": {"cta": 88}}, {"name": "Kernel", "ph": "B", "ts": 1153739.936, "pid": 0, "tid": 83, "args": {"cta": 89}}, {"name": "Kernel", "ph": "B", "ts": 1153739.936, "pid": 0, "tid": 84, "args": {"cta": 90}}, {"name": "Kernel", "ph": "B", "ts": 1153739.936, "pid": 0, "tid": 85, "args": {"cta": 91}}, {"name": "Kernel", "ph": "B", "ts": 1153739.904, "pid": 0, "tid": 86, "args": {"cta": 92}}, {"name": "Kernel", "ph": "B", "ts": 1153739.904, "pid": 0, "tid": 87, "args": {"cta": 93}}, {"name": "Kernel", "ph": "B", "ts": 1153739.808, "pid": 0, "tid": 88, "args": {"cta": 94}}, {"name": "Kernel", "ph": "B", "ts": 1153739.808, "pid": 0, "tid": 89, "args": {"cta": 95}}, {"name": "Kernel", "ph": "B", "ts": 1153739.808, "pid": 0, "tid": 90, "args": {"cta": 96}}, {"name": "Kernel", "ph": "B", "ts": 1153739.84, "pid": 0, "tid": 91, "args": {"cta": 97}}, {"name": "Kernel", "ph": "B", "ts": 1153739.808, "pid": 0, "tid": 92, "args": {"cta": 98}}, {"name": "Kernel", "ph": "B", "ts": 1153739.84, "pid": 0, "tid": 93, "args": {"cta": 99}}, {"name": "Kernel", "ph": "B", "ts": 1153739.936, "pid": 0, "tid": 94, "args": {"cta": 100}}, {"name": "Kernel", "ph": "B", "ts": 1153739.936, "pid": 0, "tid": 95, "args": {"cta": 101}}, {"name": "Kernel", "ph": "B", "ts": 1153739.936, "pid": 0, "tid": 96, "args": {"cta": 102}}, {"name": "Kernel", "ph": "B", "ts": 1153739.936, "pid": 0, "tid": 97, "args": {"cta": 103}}, {"name": "Kernel", "ph": "B", "ts": 1153739.936, "pid": 0, "tid": 98, "args": {"cta": 104}}, {"name": "Kernel", "ph": "B", "ts": 1153739.936, "pid": 0, "tid": 99, "args": {"cta": 105}}, {"name": "Kernel", "ph": "B", "ts": 1153739.936, "pid": 0, "tid": 100, "args": {"cta": 106}}, {"name": "Kernel", "ph": "B", "ts": 1153739.936, "pid": 0, "tid": 101, "args": {"cta": 107}}, {"name": "Kernel", "ph": "B", "ts": 1153739.84, "pid": 0, "tid": 102, "args": {"cta": 108}}, {"name": "Kernel", "ph": "B", "ts": 1153739.84, "pid": 0, "tid": 103, "args": {"cta": 109}}, {"name": "Kernel", "ph": "B", "ts": 1153739.84, "pid": 0, "tid": 104, "args": {"cta": 110}}, {"name": "Kernel", "ph": "B", "ts": 1153739.872, "pid": 0, "tid": 105, "args": {"cta": 111}}, {"name": "Kernel", "ph": "B", "ts": 1153739.84, "pid": 0, "tid": 106, "args": {"cta": 112}}, {"name": "Kernel", "ph": "B", "ts": 1153739.84, "pid": 0, "tid": 107, "args": {"cta": 113}}, {"name": "Kernel", "ph": "B", "ts": 1153739.904, "pid": 0, "tid": 108, "args": {"cta": 114}}, {"name": "Kernel", "ph": "B", "ts": 1153739.936, "pid": 0, "tid": 109, "args": {"cta": 115}}, {"name": "Kernel", "ph": "B", "ts": 1153739.936, "pid": 0, "tid": 110, "args": {"cta": 116}}, {"name": "Kernel", "ph": "B", "ts": 1153739.936, "pid": 0, "tid": 111, "args": {"cta": 117}}, {"name": "Kernel", "ph": "B", "ts": 1153739.904, "pid": 0, "tid": 112, "args": {"cta": 118}}, {"name": "Kernel", "ph": "B", "ts": 1153739.872, "pid": 0, "tid": 113, "args": {"cta": 119}}, {"name": "Kernel", "ph": "B", "ts": 1153739.904, "pid": 0, "tid": 114, "args": {"cta": 120}}, {"name": "Kernel", "ph": "B", "ts": 1153739.936, "pid": 0, "tid": 115, "args": {"cta": 121}}, {"name": "Kernel", "ph": "B", "ts": 1153739.84, "pid": 0, "tid": 116, "args": {"cta": 122}}, {"name": "Kernel", "ph": "B", "ts": 1153739.84, "pid": 0, "tid": 117, "args": {"cta": 123}}, {"name": "Kernel", "ph": "B", "ts": 1153739.84, "pid": 0, "tid": 118, "args": {"cta": 124}}, {"name": "Kernel", "ph": "B", "ts": 1153739.84, "pid": 0, "tid": 119, "args": {"cta": 125}}, {"name": "Kernel", "ph": "B", "ts": 1153739.84, "pid": 0, "tid": 120, "args": {"cta": 126}}, {"name": "Kernel", "ph": "B", "ts": 1153739.84, "pid": 0, "tid": 121, "args": {"cta": 127}}, {"name": "Kernel", "ph": "B", "ts": 1153739.872, "pid": 0, "tid": 122, "args": {"cta": 128}}, {"name": "Kernel", "ph": "B", "ts": 1153739.872, "pid": 0, "tid": 123, "args": {"cta": 129}}, {"name": "Kernel", "ph": "B", "ts": 1153739.904, "pid": 0, "tid": 124, "args": {"cta": 130}}, {"name": "Kernel", "ph": "B", "ts": 1153739.904, "pid": 0, "tid": 125, "args": {"cta": 131}}, {"name": "Kernel", "ph": "B", "ts": 1153739.904, "pid": 0, "tid": 126, "args": {"cta": 132}}, {"name": "Kernel", "ph": "B", "ts": 1153739.904, "pid": 0, "tid": 127, "args": {"cta": 133}}, {"name": "Kernel", "ph": "B", "ts": 1153739.84, "pid": 0, "tid": 128, "args": {"cta": 134}}, {"name": "Kernel", "ph": "B", "ts": 1153739.872, "pid": 0, "tid": 129, "args": {"cta": 135}}, {"name": "Kernel", "ph": "B", "ts": 1153739.808, "pid": 0, "tid": 130, "args": {"cta": 136}}, {"name": "Kernel", "ph": "B", "ts": 1153739.808, "pid": 0, "tid": 131, "args": {"cta": 137}}, {"name": "Kernel", "ph": "B", "ts": 1153739.808, "pid": 0, "tid": 132, "args": {"cta": 138}}, {"name": "Kernel", "ph": "B", "ts": 1153739.84, "pid": 0, "tid": 133, "args": {"cta": 139}}, {"name": "Kernel", "ph": "B", "ts": 1153739.808, "pid": 0, "tid": 134, "args": {"cta": 140}}, {"name": "Kernel", "ph": "B", "ts": 1153739.84, "pid": 0, "tid": 135, "args": {"cta": 141}}, {"name": "Kernel", "ph": "B", "ts": 1153739.84, "pid": 0, "tid": 136, "args": {"cta": 142}}, {"name": "Kernel", "ph": "B", "ts": 1153739.84, "pid": 0, "tid": 137, "args": {"cta": 143}}, {"name": "Kernel", "ph": "B", "ts": 1153739.84, "pid": 0, "tid": 138, "args": {"cta": 144}}, {"name": "Kernel", "ph": "B", "ts": 1153739.84, "pid": 0, "tid": 139, "args": {"cta": 145}}, {"name": "Kernel", "ph": "B", "ts": 1153739.84, "pid": 0, "tid": 140, "args": {"cta": 146}}, {"name": "Kernel", "ph": "B", "ts": 1153739.84, "pid": 0, "tid": 141, "args": {"cta": 147}}, {"name": "Kernel", "ph": "E", "ts": 1153765.568, "pid": 0, "tid": 142, "args": {"cta": 0}}, {"name": "Kernel", "ph": "E", "ts": 1153762.88, "pid": 0, "tid": 143, "args": {"cta": 1}}, {"name": "Kernel", "ph": "E", "ts": 1153762.944, "pid": 0, "tid": 144, "args": {"cta": 2}}, {"name": "Kernel", "ph": "E", "ts": 1153763.328, "pid": 0, "tid": 145, "args": {"cta": 3}}, {"name": "Kernel", "ph": "E", "ts": 1153763.008, "pid": 0, "tid": 146, "args": {"cta": 4}}, {"name": "Kernel", "ph": "E", "ts": 1153762.848, "pid": 0, "tid": 147, "args": {"cta": 5}}, {"name": "Kernel", "ph": "E", "ts": 1153762.912, "pid": 0, "tid": 0, "args": {"cta": 6}}, {"name": "Kernel", "ph": "E", "ts": 1153762.88, "pid": 0, "tid": 1, "args": {"cta": 7}}, {"name": "Kernel", "ph": "E", "ts": 1153763.36, "pid": 0, "tid": 2, "args": {"cta": 8}}, {"name": "Kernel", "ph": "E", "ts": 1153763.072, "pid": 0, "tid": 3, "args": {"cta": 9}}, {"name": "Kernel", "ph": "E", "ts": 1153763.072, "pid": 0, "tid": 4, "args": {"cta": 10}}, {"name": "Kernel", "ph": "E", "ts": 1153763.072, "pid": 0, "tid": 5, "args": {"cta": 11}}, {"name": "Kernel", "ph": "E", "ts": 1153763.008, "pid": 0, "tid": 6, "args": {"cta": 12}}, {"name": "Kernel", "ph": "E", "ts": 1153763.008, "pid": 0, "tid": 7, "args": {"cta": 13}}, {"name": "Kernel", "ph": "E", "ts": 1153763.008, "pid": 0, "tid": 8, "args": {"cta": 14}}, {"name": "Kernel", "ph": "E", "ts": 1153762.976, "pid": 0, "tid": 9, "args": {"cta": 15}}, {"name": "Kernel", "ph": "E", "ts": 1153763.008, "pid": 0, "tid": 10, "args": {"cta": 16}}, {"name": "Kernel", "ph": "E", "ts": 1153763.008, "pid": 0, "tid": 11, "args": {"cta": 17}}, {"name": "Kernel", "ph": "E", "ts": 1153762.88, "pid": 0, "tid": 12, "args": {"cta": 18}}, {"name": "Kernel", "ph": "E", "ts": 1153762.88, "pid": 0, "tid": 13, "args": {"cta": 19}}, {"name": "Kernel", "ph": "E", "ts": 1153762.848, "pid": 0, "tid": 14, "args": {"cta": 20}}, {"name": "Kernel", "ph": "E", "ts": 1153762.848, "pid": 0, "tid": 15, "args": {"cta": 21}}, {"name": "Kernel", "ph": "E", "ts": 1153763.008, "pid": 0, "tid": 16, "args": {"cta": 22}}, {"name": "Kernel", "ph": "E", "ts": 1153763.008, "pid": 0, "tid": 17, "args": {"cta": 23}}, {"name": "Kernel", "ph": "E", "ts": 1153763.104, "pid": 0, "tid": 18, "args": {"cta": 24}}, {"name": "Kernel", "ph": "E", "ts": 1153763.104, "pid": 0, "tid": 19, "args": {"cta": 25}}, {"name": "Kernel", "ph": "E", "ts": 1153763.072, "pid": 0, "tid": 20, "args": {"cta": 26}}, {"name": "Kernel", "ph": "E", "ts": 1153763.072, "pid": 0, "tid": 21, "args": {"cta": 27}}, {"name": "Kernel", "ph": "E", "ts": 1153763.008, "pid": 0, "tid": 22, "args": {"cta": 28}}, {"name": "Kernel", "ph": "E", "ts": 1153763.008, "pid": 0, "tid": 23, "args": {"cta": 29}}, {"name": "Kernel", "ph": "E", "ts": 1153763.008, "pid": 0, "tid": 24, "args": {"cta": 30}}, {"name": "Kernel", "ph": "E", "ts": 1153763.008, "pid": 0, "tid": 25, "args": {"cta": 31}}, {"name": "Kernel", "ph": "E", "ts": 1153763.008, "pid": 0, "tid": 26, "args": {"cta": 32}}, {"name": "Kernel", "ph": "E", "ts": 1153763.008, "pid": 0, "tid": 27, "args": {"cta": 33}}, {"name": "Kernel", "ph": "E", "ts": 1153762.88, "pid": 0, "tid": 28, "args": {"cta": 34}}, {"name": "Kernel", "ph": "E", "ts": 1153762.88, "pid": 0, "tid": 29, "args": {"cta": 35}}, {"name": "Kernel", "ph": "E", "ts": 1153762.848, "pid": 0, "tid": 30, "args": {"cta": 36}}, {"name": "Kernel", "ph": "E", "ts": 1153762.848, "pid": 0, "tid": 31, "args": {"cta": 37}}, {"name": "Kernel", "ph": "E", "ts": 1153762.88, "pid": 0, "tid": 32, "args": {"cta": 38}}, {"name": "Kernel", "ph": "E", "ts": 1153762.88, "pid": 0, "tid": 33, "args": {"cta": 39}}, {"name": "Kernel", "ph": "E", "ts": 1153763.008, "pid": 0, "tid": 34, "args": {"cta": 40}}, {"name": "Kernel", "ph": "E", "ts": 1153763.072, "pid": 0, "tid": 35, "args": {"cta": 41}}, {"name": "Kernel", "ph": "E", "ts": 1153763.072, "pid": 0, "tid": 36, "args": {"cta": 42}}, {"name": "Kernel", "ph": "E", "ts": 1153763.072, "pid": 0, "tid": 37, "args": {"cta": 43}}, {"name": "Kernel", "ph": "E", "ts": 1153763.328, "pid": 0, "tid": 38, "args": {"cta": 44}}, {"name": "Kernel", "ph": "E", "ts": 1153763.328, "pid": 0, "tid": 39, "args": {"cta": 45}}, {"name": "Kernel", "ph": "E", "ts": 1153763.328, "pid": 0, "tid": 40, "args": {"cta": 46}}, {"name": "Kernel", "ph": "E", "ts": 1153763.328, "pid": 0, "tid": 41, "args": {"cta": 47}}, {"name": "Kernel", "ph": "E", "ts": 1153762.912, "pid": 0, "tid": 42, "args": {"cta": 48}}, {"name": "Kernel", "ph": "E", "ts": 1153762.912, "pid": 0, "tid": 43, "args": {"cta": 49}}, {"name": "Kernel", "ph": "E", "ts": 1153762.848, "pid": 0, "tid": 44, "args": {"cta": 50}}, {"name": "Kernel", "ph": "E", "ts": 1153762.848, "pid": 0, "tid": 45, "args": {"cta": 51}}, {"name": "Kernel", "ph": "E", "ts": 1153762.88, "pid": 0, "tid": 46, "args": {"cta": 52}}, {"name": "Kernel", "ph": "E", "ts": 1153762.88, "pid": 0, "tid": 47, "args": {"cta": 53}}, {"name": "Kernel", "ph": "E", "ts": 1153762.88, "pid": 0, "tid": 48, "args": {"cta": 54}}, {"name": "Kernel", "ph": "E", "ts": 1153762.88, "pid": 0, "tid": 49, "args": {"cta": 55}}, {"name": "Kernel", "ph": "E", "ts": 1153763.104, "pid": 0, "tid": 50, "args": {"cta": 56}}, {"name": "Kernel", "ph": "E", "ts": 1153763.136, "pid": 0, "tid": 51, "args": {"cta": 57}}, {"name": "Kernel", "ph": "E", "ts": 1153763.136, "pid": 0, "tid": 52, "args": {"cta": 58}}, {"name": "Kernel", "ph": "E", "ts": 1153763.136, "pid": 0, "tid": 53, "args": {"cta": 59}}, {"name": "Kernel", "ph": "E", "ts": 1153763.328, "pid": 0, "tid": 54, "args": {"cta": 60}}, {"name": "Kernel", "ph": "E", "ts": 1153762.976, "pid": 0, "tid": 55, "args": {"cta": 61}}, {"name": "Kernel", "ph": "E", "ts": 1153763.328, "pid": 0, "tid": 56, "args": {"cta": 62}}, {"name": "Kernel", "ph": "E", "ts": 1153762.976, "pid": 0, "tid": 57, "args": {"cta": 63}}, {"name": "Kernel", "ph": "E", "ts": 1153762.912, "pid": 0, "tid": 58, "args": {"cta": 64}}, {"name": "Kernel", "ph": "E", "ts": 1153762.912, "pid": 0, "tid": 59, "args": {"cta": 65}}, {"name": "Kernel", "ph": "E", "ts": 1153762.976, "pid": 0, "tid": 60, "args": {"cta": 66}}, {"name": "Kernel", "ph": "E", "ts": 1153762.976, "pid": 0, "tid": 61, "args": {"cta": 67}}, {"name": "Kernel", "ph": "E", "ts": 1153762.944, "pid": 0, "tid": 62, "args": {"cta": 68}}, {"name": "Kernel", "ph": "E", "ts": 1153762.944, "pid": 0, "tid": 63, "args": {"cta": 69}}, {"name": "Kernel", "ph": "E", "ts": 1153762.944, "pid": 0, "tid": 64, "args": {"cta": 70}}, {"name": "Kernel", "ph": "E", "ts": 1153762.912, "pid": 0, "tid": 65, "args": {"cta": 71}}, {"name": "Kernel", "ph": "E", "ts": 1153763.04, "pid": 0, "tid": 66, "args": {"cta": 72}}, {"name": "Kernel", "ph": "E", "ts": 1153763.04, "pid": 0, "tid": 67, "args": {"cta": 73}}, {"name": "Kernel", "ph": "E", "ts": 1153763.04, "pid": 0, "tid": 68, "args": {"cta": 74}}, {"name": "Kernel", "ph": "E", "ts": 1153763.04, "pid": 0, "tid": 69, "args": {"cta": 75}}, {"name": "Kernel", "ph": "E", "ts": 1153763.008, "pid": 0, "tid": 70, "args": {"cta": 76}}, {"name": "Kernel", "ph": "E", "ts": 1153763.008, "pid": 0, "tid": 71, "args": {"cta": 77}}, {"name": "Kernel", "ph": "E", "ts": 1153763.04, "pid": 0, "tid": 72, "args": {"cta": 78}}, {"name": "Kernel", "ph": "E", "ts": 1153763.04, "pid": 0, "tid": 73, "args": {"cta": 79}}, {"name": "Kernel", "ph": "E", "ts": 1153763.008, "pid": 0, "tid": 74, "args": {"cta": 80}}, {"name": "Kernel", "ph": "E", "ts": 1153763.008, "pid": 0, "tid": 75, "args": {"cta": 81}}, {"name": "Kernel", "ph": "E", "ts": 1153762.912, "pid": 0, "tid": 76, "args": {"cta": 82}}, {"name": "Kernel", "ph": "E", "ts": 1153762.912, "pid": 0, "tid": 77, "args": {"cta": 83}}, {"name": "Kernel", "ph": "E", "ts": 1153762.88, "pid": 0, "tid": 78, "args": {"cta": 84}}, {"name": "Kernel", "ph": "E", "ts": 1153762.88, "pid": 0, "tid": 79, "args": {"cta": 85}}, {"name": "Kernel", "ph": "E", "ts": 1153763.072, "pid": 0, "tid": 80, "args": {"cta": 86}}, {"name": "Kernel", "ph": "E", "ts": 1153763.072, "pid": 0, "tid": 81, "args": {"cta": 87}}, {"name": "Kernel", "ph": "E", "ts": 1153763.136, "pid": 0, "tid": 82, "args": {"cta": 88}}, {"name": "Kernel", "ph": "E", "ts": 1153763.136, "pid": 0, "tid": 83, "args": {"cta": 89}}, {"name": "Kernel", "ph": "E", "ts": 1153763.008, "pid": 0, "tid": 84, "args": {"cta": 90}}, {"name": "Kernel", "ph": "E", "ts": 1153763.008, "pid": 0, "tid": 85, "args": {"cta": 91}}, {"name": "Kernel", "ph": "E", "ts": 1153763.008, "pid": 0, "tid": 86, "args": {"cta": 92}}, {"name": "Kernel", "ph": "E", "ts": 1153763.008, "pid": 0, "tid": 87, "args": {"cta": 93}}, {"name": "Kernel", "ph": "E", "ts": 1153763.008, "pid": 0, "tid": 88, "args": {"cta": 94}}, {"name": "Kernel", "ph": "E", "ts": 1153763.008, "pid": 0, "tid": 89, "args": {"cta": 95}}, {"name": "Kernel", "ph": "E", "ts": 1153762.912, "pid": 0, "tid": 90, "args": {"cta": 96}}, {"name": "Kernel", "ph": "E", "ts": 1153762.912, "pid": 0, "tid": 91, "args": {"cta": 97}}, {"name": "Kernel", "ph": "E", "ts": 1153762.88, "pid": 0, "tid": 92, "args": {"cta": 98}}, {"name": "Kernel", "ph": "E", "ts": 1153762.912, "pid": 0, "tid": 93, "args": {"cta": 99}}, {"name": "Kernel", "ph": "E", "ts": 1153763.136, "pid": 0, "tid": 94, "args": {"cta": 100}}, {"name": "Kernel", "ph": "E", "ts": 1153763.136, "pid": 0, "tid": 95, "args": {"cta": 101}}, {"name": "Kernel", "ph": "E", "ts": 1153763.136, "pid": 0, "tid": 96, "args": {"cta": 102}}, {"name": "Kernel", "ph": "E", "ts": 1153763.136, "pid": 0, "tid": 97, "args": {"cta": 103}}, {"name": "Kernel", "ph": "E", "ts": 1153763.328, "pid": 0, "tid": 98, "args": {"cta": 104}}, {"name": "Kernel", "ph": "E", "ts": 1153763.328, "pid": 0, "tid": 99, "args": {"cta": 105}}, {"name": "Kernel", "ph": "E", "ts": 1153762.976, "pid": 0, "tid": 100, "args": {"cta": 106}}, {"name": "Kernel", "ph": "E", "ts": 1153763.008, "pid": 0, "tid": 101, "args": {"cta": 107}}, {"name": "Kernel", "ph": "E", "ts": 1153762.944, "pid": 0, "tid": 102, "args": {"cta": 108}}, {"name": "Kernel", "ph": "E", "ts": 1153762.944, "pid": 0, "tid": 103, "args": {"cta": 109}}, {"name": "Kernel", "ph": "E", "ts": 1153762.944, "pid": 0, "tid": 104, "args": {"cta": 110}}, {"name": "Kernel", "ph": "E", "ts": 1153762.944, "pid": 0, "tid": 105, "args": {"cta": 111}}, {"name": "Kernel", "ph": "E", "ts": 1153762.912, "pid": 0, "tid": 106, "args": {"cta": 112}}, {"name": "Kernel", "ph": "E", "ts": 1153762.912, "pid": 0, "tid": 107, "args": {"cta": 113}}, {"name": "Kernel", "ph": "E", "ts": 1153763.072, "pid": 0, "tid": 108, "args": {"cta": 114}}, {"name": "Kernel", "ph": "E", "ts": 1153763.104, "pid": 0, "tid": 109, "args": {"cta": 115}}, {"name": "Kernel", "ph": "E", "ts": 1153763.104, "pid": 0, "tid": 110, "args": {"cta": 116}}, {"name": "Kernel", "ph": "E", "ts": 1153763.136, "pid": 0, "tid": 111, "args": {"cta": 117}}, {"name": "Kernel", "ph": "E", "ts": 1153762.976, "pid": 0, "tid": 112, "args": {"cta": 118}}, {"name": "Kernel", "ph": "E", "ts": 1153763.328, "pid": 0, "tid": 113, "args": {"cta": 119}}, {"name": "Kernel", "ph": "E", "ts": 1153763.328, "pid": 0, "tid": 114, "args": {"cta": 120}}, {"name": "Kernel", "ph": "E", "ts": 1153763.328, "pid": 0, "tid": 115, "args": {"cta": 121}}, {"name": "Kernel", "ph": "E", "ts": 1153762.88, "pid": 0, "tid": 116, "args": {"cta": 122}}, {"name": "Kernel", "ph": "E", "ts": 1153762.88, "pid": 0, "tid": 117, "args": {"cta": 123}}, {"name": "Kernel", "ph": "E", "ts": 1153762.912, "pid": 0, "tid": 118, "args": {"cta": 124}}, {"name": "Kernel", "ph": "E", "ts": 1153762.912, "pid": 0, "tid": 119, "args": {"cta": 125}}, {"name": "Kernel", "ph": "E", "ts": 1153762.88, "pid": 0, "tid": 120, "args": {"cta": 126}}, {"name": "Kernel", "ph": "E", "ts": 1153762.912, "pid": 0, "tid": 121, "args": {"cta": 127}}, {"name": "Kernel", "ph": "E", "ts": 1153763.008, "pid": 0, "tid": 122, "args": {"cta": 128}}, {"name": "Kernel", "ph": "E", "ts": 1153763.04, "pid": 0, "tid": 123, "args": {"cta": 129}}, {"name": "Kernel", "ph": "E", "ts": 1153763.072, "pid": 0, "tid": 124, "args": {"cta": 130}}, {"name": "Kernel", "ph": "E", "ts": 1153763.104, "pid": 0, "tid": 125, "args": {"cta": 131}}, {"name": "Kernel", "ph": "E", "ts": 1153763.328, "pid": 0, "tid": 126, "args": {"cta": 132}}, {"name": "Kernel", "ph": "E", "ts": 1153763.328, "pid": 0, "tid": 127, "args": {"cta": 133}}, {"name": "Kernel", "ph": "E", "ts": 1153762.976, "pid": 0, "tid": 128, "args": {"cta": 134}}, {"name": "Kernel", "ph": "E", "ts": 1153762.976, "pid": 0, "tid": 129, "args": {"cta": 135}}, {"name": "Kernel", "ph": "E", "ts": 1153762.912, "pid": 0, "tid": 130, "args": {"cta": 136}}, {"name": "Kernel", "ph": "E", "ts": 1153762.944, "pid": 0, "tid": 131, "args": {"cta": 137}}, {"name": "Kernel", "ph": "E", "ts": 1153762.848, "pid": 0, "tid": 132, "args": {"cta": 138}}, {"name": "Kernel", "ph": "E", "ts": 1153762.848, "pid": 0, "tid": 133, "args": {"cta": 139}}, {"name": "Kernel", "ph": "E", "ts": 1153762.848, "pid": 0, "tid": 134, "args": {"cta": 140}}, {"name": "Kernel", "ph": "E", "ts": 1153762.848, "pid": 0, "tid": 135, "args": {"cta": 141}}, {"name": "Kernel", "ph": "E", "ts": 1153762.912, "pid": 0, "tid": 136, "args": {"cta": 142}}, {"name": "Kernel", "ph": "E", "ts": 1153762.944, "pid": 0, "tid": 137, "args": {"cta": 143}}, {"name": "Kernel", "ph": "E", "ts": 1153762.88, "pid": 0, "tid": 138, "args": {"cta": 144}}, {"name": "Kernel", "ph": "E", "ts": 1153762.88, "pid": 0, "tid": 139, "args": {"cta": 145}}, {"name": "Kernel", "ph": "E", "ts": 1153762.88, "pid": 0, "tid": 140, "args": {"cta": 146}}, {"name": "Kernel", "ph": "E", "ts": 1153762.88, "pid": 0, "tid": 141, "args": {"cta": 147}}, {"name": "process_name", "ph": "M", "pid": 0, "args": {"name": "MegaMoE (per-SM)"}}, {"name": "thread_name", "ph": "M", "pid": 0, "tid": 0, "args": {"name": "SM 000"}}, {"name": "thread_sort_index", "ph": "M", "pid": 0, "tid": 0, "args": {"sort_index": 0}}, {"name": "thread_name", "ph": "M", "pid": 0, "tid": 1, "args": {"name": "SM 001"}}, {"name": "thread_sort_index", "ph": "M", "pid": 0, "tid": 1, "args": {"sort_index": 1}}, {"name": "thread_name", "ph": "M", "pid": 0, "tid": 2, "args": {"name": "SM 002"}}, {"name": "thread_sort_index", "ph": "M", "pid": 0, "tid": 2, "args": {"sort_index": 2}}, {"name": "thread_name", "ph": "M", "pid": 0, "tid": 3, "args": {"name": "SM 003"}}, {"name": "thread_sort_index", "ph": "M", "pid": 0, "tid": 3, "args": {"sort_index": 3}}, {"name": "thread_name", "ph": "M", "pid": 0, "tid": 4, "args": {"name": "SM 004"}}, {"name": "thread_sort_index", "ph": "M", "pid": 0, "tid": 4, "args": {"sort_index": 4}}, {"name": "thread_name", "ph": "M", "pid": 0, "tid": 5, "args": {"name": "SM 005"}}, {"name": "thread_sort_index", "ph": "M", "pid": 0, "tid": 5, "args": {"sort_index": 5}}, {"name": "thread_name", "ph": "M", "pid": 0, "tid": 6, "args": {"name": "SM 006"}}, {"name": "thread_sort_index", "ph": "M", "pid": 0, "tid": 6, "args": {"sort_index": 6}}, {"name": "thread_name", "ph": "M", "pid": 0, "tid": 7, "args": {"name": "SM 007"}}, {"name": "thread_sort_index", "ph": "M", "pid": 0, "tid": 7, "args": {"sort_index": 7}}, {"name": "thread_name", "ph": "M", "pid": 0, "tid": 8, "args": {"name": "SM 008"}}, {"name": "thread_sort_index", "ph": "M", "pid": 0, "tid": 8, "args": {"sort_index": 8}}, {"name": "thread_name", "ph": "M", "pid": 0, "tid": 9, "args": {"name": "SM 009"}}, {"name": "thread_sort_index", "ph": "M", "pid": 0, "tid": 9, "args": {"sort_index": 9}}, {"name": "thread_name", "ph": "M", "pid": 0, "tid": 10, "args": {"name": "SM 010"}}, {"name": "thread_sort_index", "ph": "M", "pid": 0, "tid": 10, "args": {"sort_index": 10}}, {"name": "thread_name", "ph": "M", "pid": 0, "tid": 11, "args": {"name": "SM 011"}}, {"name": "thread_sort_index", "ph": "M", "pid": 0, "tid": 11, "args": {"sort_index": 11}}, {"name": "thread_name", "ph": "M", "pid": 0, "tid": 12, "args": {"name": "SM 012"}}, {"name": "thread_sort_index", "ph": "M", "pid": 0, "tid": 12, "args": {"sort_index": 12}}, {"name": "thread_name", "ph": "M", "pid": 0, "tid": 13, "args": {"name": "SM 013"}}, {"name": "thread_sort_index", "ph": "M", "pid": 0, "tid": 13, "args": {"sort_index": 13}}, {"name": "thread_name", "ph": "M", "pid": 0, "tid": 14, "args": {"name": "SM 014"}}, {"name": "thread_sort_index", "ph": "M", "pid": 0, "tid": 14, "args": {"sort_index": 14}}, {"name": "thread_name", "ph": "M", "pid": 0, "tid": 15, "args": {"name": "SM 015"}}, {"name": "thread_sort_index", "ph": "M", "pid": 0, "tid": 15, "args": {"sort_index": 15}}, {"name": "thread_name", "ph": "M", "pid": 0, "tid": 16, "args": {"name": "SM 016"}}, {"name": "thread_sort_index", "ph": "M", "pid": 0, "tid": 16, "args": {"sort_index": 16}}, {"name": "thread_name", "ph": "M", "pid": 0, "tid": 17, "args": {"name": "SM 017"}}, {"name": "thread_sort_index", "ph": "M", "pid": 0, "tid": 17, "args": {"sort_index": 17}}, {"name": "thread_name", "ph": "M", "pid": 0, "tid": 18, "args": {"name": "SM 018"}}, {"name": "thread_sort_index", "ph": "M", "pid": 0, "tid": 18, "args": {"sort_index": 18}}, {"name": "thread_name", "ph": "M", "pid": 0, "tid": 19, "args": {"name": "SM 019"}}, {"name": "thread_sort_index", "ph": "M", "pid": 0, "tid": 19, "args": {"sort_index": 19}}, {"name": "thread_name", "ph": "M", "pid": 0, "tid": 20, "args": {"name": "SM 020"}}, {"name": "thread_sort_index", "ph": "M", "pid": 0, "tid": 20, "args": {"sort_index": 20}}, {"name": "thread_name", "ph": "M", "pid": 0, "tid": 21, "args": {"name": "SM 021"}}, {"name": "thread_sort_index", "ph": "M", "pid": 0, "tid": 21, "args": {"sort_index": 21}}, {"name": "thread_name", "ph": "M", "pid": 0, "tid": 22, "args": {"name": "SM 022"}}, {"name": "thread_sort_index", "ph": "M", "pid": 0, "tid": 22, "args": {"sort_index": 22}}, {"name": "thread_name", "ph": "M", "pid": 0, "tid": 23, "args": {"name": "SM 023"}}, {"name": "thread_sort_index", "ph": "M", "pid": 0, "tid": 23, "args": {"sort_index": 23}}, {"name": "thread_name", "ph": "M", "pid": 0, "tid": 24, "args": {"name": "SM 024"}}, {"name": "thread_sort_index", "ph": "M", "pid": 0, "tid": 24, "args": {"sort_index": 24}}, {"name": "thread_name", "ph": "M", "pid": 0, "tid": 25, "args": {"name": "SM 025"}}, {"name": "thread_sort_index", "ph": "M", "pid": 0, "tid": 25, "args": {"sort_index": 25}}, {"name": "thread_name", "ph": "M", "pid": 0, "tid": 26, "args": {"name": "SM 026"}}, {"name": "thread_sort_index", "ph": "M", "pid": 0, "tid": 26, "args": {"sort_index": 26}}, {"name": "thread_name", "ph": "M", "pid": 0, "tid": 27, "args": {"name": "SM 027"}}, {"name": "thread_sort_index", "ph": "M", "pid": 0, "tid": 27, "args": {"sort_index": 27}}, {"name": "thread_name", "ph": "M", "pid": 0, "tid": 28, "args": {"name": "SM 028"}}, {"name": "thread_sort_index", "ph": "M", "pid": 0, "tid": 28, "args": {"sort_index": 28}}, {"name": "thread_name", "ph": "M", "pid": 0, "tid": 29, "args": {"name": "SM 029"}}, {"name": "thread_sort_index", "ph": "M", "pid": 0, "tid": 29, "args": {"sort_index": 29}}, {"name": "thread_name", "ph": "M", "pid": 0, "tid": 30, "args": {"name": "SM 030"}}, {"name": "thread_sort_index", "ph": "M", "pid": 0, "tid": 30, "args": {"sort_index": 30}}, {"name": "thread_name", "ph": "M", "pid": 0, "tid": 31, "args": {"name": "SM 031"}}, {"name": "thread_sort_index", "ph": "M", "pid": 0, "tid": 31, "args": {"sort_index": 31}}, {"name": "thread_name", "ph": "M", "pid": 0, "tid": 32, "args": {"name": "SM 032"}}, {"name": "thread_sort_index", "ph": "M", "pid": 0, "tid": 32, "args": {"sort_index": 32}}, {"name": "thread_name", "ph": "M", "pid": 0, "tid": 33, "args": {"name": "SM 033"}}, {"name": "thread_sort_index", "ph": "M", "pid": 0, "tid": 33, "args": {"sort_index": 33}}, {"name": "thread_name", "ph": "M", "pid": 0, "tid": 34, "args": {"name": "SM 034"}}, {"name": "thread_sort_index", "ph": "M", "pid": 0, "tid": 34, "args": {"sort_index": 34}}, {"name": "thread_name", "ph": "M", "pid": 0, "tid": 35, "args": {"name": "SM 035"}}, {"name": "thread_sort_index", "ph": "M", "pid": 0, "tid": 35, "args": {"sort_index": 35}}, {"name": "thread_name", "ph": "M", "pid": 0, "tid": 36, "args": {"name": "SM 036"}}, {"name": "thread_sort_index", "ph": "M", "pid": 0, "tid": 36, "args": {"sort_index": 36}}, {"name": "thread_name", "ph": "M", "pid": 0, "tid": 37, "args": {"name": "SM 037"}}, {"name": "thread_sort_index", "ph": "M", "pid": 0, "tid": 37, "args": {"sort_index": 37}}, {"name": "thread_name", "ph": "M", "pid": 0, "tid": 38, "args": {"name": "SM 038"}}, {"name": "thread_sort_index", "ph": "M", "pid": 0, "tid": 38, "args": {"sort_index": 38}}, {"name": "thread_name", "ph": "M", "pid": 0, "tid": 39, "args": {"name": "SM 039"}}, {"name": "thread_sort_index", "ph": "M", "pid": 0, "tid": 39, "args": {"sort_index": 39}}, {"name": "thread_name", "ph": "M", "pid": 0, "tid": 40, "args": {"name": "SM 040"}}, {"name": "thread_sort_index", "ph": "M", "pid": 0, "tid": 40, "args": {"sort_index": 40}}, {"name": "thread_name", "ph": "M", "pid": 0, "tid": 41, "args": {"name": "SM 041"}}, {"name": "thread_sort_index", "ph": "M", "pid": 0, "tid": 41, "args": {"sort_index": 41}}, {"name": "thread_name", "ph": "M", "pid": 0, "tid": 42, "args": {"name": "SM 042"}}, {"name": "thread_sort_index", "ph": "M", "pid": 0, "tid": 42, "args": {"sort_index": 42}}, {"name": "thread_name", "ph": "M", "pid": 0, "tid": 43, "args": {"name": "SM 043"}}, {"name": "thread_sort_index", "ph": "M", "pid": 0, "tid": 43, "args": {"sort_index": 43}}, {"name": "thread_name", "ph": "M", "pid": 0, "tid": 44, "args": {"name": "SM 044"}}, {"name": "thread_sort_index", "ph": "M", "pid": 0, "tid": 44, "args": {"sort_index": 44}}, {"name": "thread_name", "ph": "M", "pid": 0, "tid": 45, "args": {"name": "SM 045"}}, {"name": "thread_sort_index", "ph": "M", "pid": 0, "tid": 45, "args": {"sort_index": 45}}, {"name": "thread_name", "ph": "M", "pid": 0, "tid": 46, "args": {"name": "SM 046"}}, {"name": "thread_sort_index", "ph": "M", "pid": 0, "tid": 46, "args": {"sort_index": 46}}, {"name": "thread_name", "ph": "M", "pid": 0, "tid": 47, "args": {"name": "SM 047"}}, {"name": "thread_sort_index", "ph": "M", "pid": 0, "tid": 47, "args": {"sort_index": 47}}, {"name": "thread_name", "ph": "M", "pid": 0, "tid": 48, "args": {"name": "SM 048"}}, {"name": "thread_sort_index", "ph": "M", "pid": 0, "tid": 48, "args": {"sort_index": 48}}, {"name": "thread_name", "ph": "M", "pid": 0, "tid": 49, "args": {"name": "SM 049"}}, {"name": "thread_sort_index", "ph": "M", "pid": 0, "tid": 49, "args": {"sort_index": 49}}, {"name": "thread_name", "ph": "M", "pid": 0, "tid": 50, "args": {"name": "SM 050"}}, {"name": "thread_sort_index", "ph": "M", "pid": 0, "tid": 50, "args": {"sort_index": 50}}, {"name": "thread_name", "ph": "M", "pid": 0, "tid": 51, "args": {"name": "SM 051"}}, {"name": "thread_sort_index", "ph": "M", "pid": 0, "tid": 51, "args": {"sort_index": 51}}, {"name": "thread_name", "ph": "M", "pid": 0, "tid": 52, "args": {"name": "SM 052"}}, {"name": "thread_sort_index", "ph": "M", "pid": 0, "tid": 52, "args": {"sort_index": 52}}, {"name": "thread_name", "ph": "M", "pid": 0, "tid": 53, "args": {"name": "SM 053"}}, {"name": "thread_sort_index", "ph": "M", "pid": 0, "tid": 53, "args": {"sort_index": 53}}, {"name": "thread_name", "ph": "M", "pid": 0, "tid": 54, "args": {"name": "SM 054"}}, {"name": "thread_sort_index", "ph": "M", "pid": 0, "tid": 54, "args": {"sort_index": 54}}, {"name": "thread_name", "ph": "M", "pid": 0, "tid": 55, "args": {"name": "SM 055"}}, {"name": "thread_sort_index", "ph": "M", "pid": 0, "tid": 55, "args": {"sort_index": 55}}, {"name": "thread_name", "ph": "M", "pid": 0, "tid": 56, "args": {"name": "SM 056"}}, {"name": "thread_sort_index", "ph": "M", "pid": 0, "tid": 56, "args": {"sort_index": 56}}, {"name": "thread_name", "ph": "M", "pid": 0, "tid": 57, "args": {"name": "SM 057"}}, {"name": "thread_sort_index", "ph": "M", "pid": 0, "tid": 57, "args": {"sort_index": 57}}, {"name": "thread_name", "ph": "M", "pid": 0, "tid": 58, "args": {"name": "SM 058"}}, {"name": "thread_sort_index", "ph": "M", "pid": 0, "tid": 58, "args": {"sort_index": 58}}, {"name": "thread_name", "ph": "M", "pid": 0, "tid": 59, "args": {"name": "SM 059"}}, {"name": "thread_sort_index", "ph": "M", "pid": 0, "tid": 59, "args": {"sort_index": 59}}, {"name": "thread_name", "ph": "M", "pid": 0, "tid": 60, "args": {"name": "SM 060"}}, {"name": "thread_sort_index", "ph": "M", "pid": 0, "tid": 60, "args": {"sort_index": 60}}, {"name": "thread_name", "ph": "M", "pid": 0, "tid": 61, "args": {"name": "SM 061"}}, {"name": "thread_sort_index", "ph": "M", "pid": 0, "tid": 61, "args": {"sort_index": 61}}, {"name": "thread_name", "ph": "M", "pid": 0, "tid": 62, "args": {"name": "SM 062"}}, {"name": "thread_sort_index", "ph": "M", "pid": 0, "tid": 62, "args": {"sort_index": 62}}, {"name": "thread_name", "ph": "M", "pid": 0, "tid": 63, "args": {"name": "SM 063"}}, {"name": "thread_sort_index", "ph": "M", "pid": 0, "tid": 63, "args": {"sort_index": 63}}, {"name": "thread_name", "ph": "M", "pid": 0, "tid": 64, "args": {"name": "SM 064"}}, {"name": "thread_sort_index", "ph": "M", "pid": 0, "tid": 64, "args": {"sort_index": 64}}, {"name": "thread_name", "ph": "M", "pid": 0, "tid": 65, "args": {"name": "SM 065"}}, {"name": "thread_sort_index", "ph": "M", "pid": 0, "tid": 65, "args": {"sort_index": 65}}, {"name": "thread_name", "ph": "M", "pid": 0, "tid": 66, "args": {"name": "SM 066"}}, {"name": "thread_sort_index", "ph": "M", "pid": 0, "tid": 66, "args": {"sort_index": 66}}, {"name": "thread_name", "ph": "M", "pid": 0, "tid": 67, "args": {"name": "SM 067"}}, {"name": "thread_sort_index", "ph": "M", "pid": 0, "tid": 67, "args": {"sort_index": 67}}, {"name": "thread_name", "ph": "M", "pid": 0, "tid": 68, "args": {"name": "SM 068"}}, {"name": "thread_sort_index", "ph": "M", "pid": 0, "tid": 68, "args": {"sort_index": 68}}, {"name": "thread_name", "ph": "M", "pid": 0, "tid": 69, "args": {"name": "SM 069"}}, {"name": "thread_sort_index", "ph": "M", "pid": 0, "tid": 69, "args": {"sort_index": 69}}, {"name": "thread_name", "ph": "M", "pid": 0, "tid": 70, "args": {"name": "SM 070"}}, {"name": "thread_sort_index", "ph": "M", "pid": 0, "tid": 70, "args": {"sort_index": 70}}, {"name": "thread_name", "ph": "M", "pid": 0, "tid": 71, "args": {"name": "SM 071"}}, {"name": "thread_sort_index", "ph": "M", "pid": 0, "tid": 71, "args": {"sort_index": 71}}, {"name": "thread_name", "ph": "M", "pid": 0, "tid": 72, "args": {"name": "SM 072"}}, {"name": "thread_sort_index", "ph": "M", "pid": 0, "tid": 72, "args": {"sort_index": 72}}, {"name": "thread_name", "ph": "M", "pid": 0, "tid": 73, "args": {"name": "SM 073"}}, {"name": "thread_sort_index", "ph": "M", "pid": 0, "tid": 73, "args": {"sort_index": 73}}, {"name": "thread_name", "ph": "M", "pid": 0, "tid": 74, "args": {"name": "SM 074"}}, {"name": "thread_sort_index", "ph": "M", "pid": 0, "tid": 74, "args": {"sort_index": 74}}, {"name": "thread_name", "ph": "M", "pid": 0, "tid": 75, "args": {"name": "SM 075"}}, {"name": "thread_sort_index", "ph": "M", "pid": 0, "tid": 75, "args": {"sort_index": 75}}, {"name": "thread_name", "ph": "M", "pid": 0, "tid": 76, "args": {"name": "SM 076"}}, {"name": "thread_sort_index", "ph": "M", "pid": 0, "tid": 76, "args": {"sort_index": 76}}, {"name": "thread_name", "ph": "M", "pid": 0, "tid": 77, "args": {"name": "SM 077"}}, {"name": "thread_sort_index", "ph": "M", "pid": 0, "tid": 77, "args": {"sort_index": 77}}, {"name": "thread_name", "ph": "M", "pid": 0, "tid": 78, "args": {"name": "SM 078"}}, {"name": "thread_sort_index", "ph": "M", "pid": 0, "tid": 78, "args": {"sort_index": 78}}, {"name": "thread_name", "ph": "M", "pid": 0, "tid": 79, "args": {"name": "SM 079"}}, {"name": "thread_sort_index", "ph": "M", "pid": 0, "tid": 79, "args": {"sort_index": 79}}, {"name": "thread_name", "ph": "M", "pid": 0, "tid": 80, "args": {"name": "SM 080"}}, {"name": "thread_sort_index", "ph": "M", "pid": 0, "tid": 80, "args": {"sort_index": 80}}, {"name": "thread_name", "ph": "M", "pid": 0, "tid": 81, "args": {"name": "SM 081"}}, {"name": "thread_sort_index", "ph": "M", "pid": 0, "tid": 81, "args": {"sort_index": 81}}, {"name": "thread_name", "ph": "M", "pid": 0, "tid": 82, "args": {"name": "SM 082"}}, {"name": "thread_sort_index", "ph": "M", "pid": 0, "tid": 82, "args": {"sort_index": 82}}, {"name": "thread_name", "ph": "M", "pid": 0, "tid": 83, "args": {"name": "SM 083"}}, {"name": "thread_sort_index", "ph": "M", "pid": 0, "tid": 83, "args": {"sort_index": 83}}, {"name": "thread_name", "ph": "M", "pid": 0, "tid": 84, "args": {"name": "SM 084"}}, {"name": "thread_sort_index", "ph": "M", "pid": 0, "tid": 84, "args": {"sort_index": 84}}, {"name": "thread_name", "ph": "M", "pid": 0, "tid": 85, "args": {"name": "SM 085"}}, {"name": "thread_sort_index", "ph": "M", "pid": 0, "tid": 85, "args": {"sort_index": 85}}, {"name": "thread_name", "ph": "M", "pid": 0, "tid": 86, "args": {"name": "SM 086"}}, {"name": "thread_sort_index", "ph": "M", "pid": 0, "tid": 86, "args": {"sort_index": 86}}, {"name": "thread_name", "ph": "M", "pid": 0, "tid": 87, "args": {"name": "SM 087"}}, {"name": "thread_sort_index", "ph": "M", "pid": 0, "tid": 87, "args": {"sort_index": 87}}, {"name": "thread_name", "ph": "M", "pid": 0, "tid": 88, "args": {"name": "SM 088"}}, {"name": "thread_sort_index", "ph": "M", "pid": 0, "tid": 88, "args": {"sort_index": 88}}, {"name": "thread_name", "ph": "M", "pid": 0, "tid": 89, "args": {"name": "SM 089"}}, {"name": "thread_sort_index", "ph": "M", "pid": 0, "tid": 89, "args": {"sort_index": 89}}, {"name": "thread_name", "ph": "M", "pid": 0, "tid": 90, "args": {"name": "SM 090"}}, {"name": "thread_sort_index", "ph": "M", "pid": 0, "tid": 90, "args": {"sort_index": 90}}, {"name": "thread_name", "ph": "M", "pid": 0, "tid": 91, "args": {"name": "SM 091"}}, {"name": "thread_sort_index", "ph": "M", "pid": 0, "tid": 91, "args": {"sort_index": 91}}, {"name": "thread_name", "ph": "M", "pid": 0, "tid": 92, "args": {"name": "SM 092"}}, {"name": "thread_sort_index", "ph": "M", "pid": 0, "tid": 92, "args": {"sort_index": 92}}, {"name": "thread_name", "ph": "M", "pid": 0, "tid": 93, "args": {"name": "SM 093"}}, {"name": "thread_sort_index", "ph": "M", "pid": 0, "tid": 93, "args": {"sort_index": 93}}, {"name": "thread_name", "ph": "M", "pid": 0, "tid": 94, "args": {"name": "SM 094"}}, {"name": "thread_sort_index", "ph": "M", "pid": 0, "tid": 94, "args": {"sort_index": 94}}, {"name": "thread_name", "ph": "M", "pid": 0, "tid": 95, "args": {"name": "SM 095"}}, {"name": "thread_sort_index", "ph": "M", "pid": 0, "tid": 95, "args": {"sort_index": 95}}, {"name": "thread_name", "ph": "M", "pid": 0, "tid": 96, "args": {"name": "SM 096"}}, {"name": "thread_sort_index", "ph": "M", "pid": 0, "tid": 96, "args": {"sort_index": 96}}, {"name": "thread_name", "ph": "M", "pid": 0, "tid": 97, "args": {"name": "SM 097"}}, {"name": "thread_sort_index", "ph": "M", "pid": 0, "tid": 97, "args": {"sort_index": 97}}, {"name": "thread_name", "ph": "M", "pid": 0, "tid": 98, "args": {"name": "SM 098"}}, {"name": "thread_sort_index", "ph": "M", "pid": 0, "tid": 98, "args": {"sort_index": 98}}, {"name": "thread_name", "ph": "M", "pid": 0, "tid": 99, "args": {"name": "SM 099"}}, {"name": "thread_sort_index", "ph": "M", "pid": 0, "tid": 99, "args": {"sort_index": 99}}, {"name": "thread_name", "ph": "M", "pid": 0, "tid": 100, "args": {"name": "SM 100"}}, {"name": "thread_sort_index", "ph": "M", "pid": 0, "tid": 100, "args": {"sort_index": 100}}, {"name": "thread_name", "ph": "M", "pid": 0, "tid": 101, "args": {"name": "SM 101"}}, {"name": "thread_sort_index", "ph": "M", "pid": 0, "tid": 101, "args": {"sort_index": 101}}, {"name": "thread_name", "ph": "M", "pid": 0, "tid": 102, "args": {"name": "SM 102"}}, {"name": "thread_sort_index", "ph": "M", "pid": 0, "tid": 102, "args": {"sort_index": 102}}, {"name": "thread_name", "ph": "M", "pid": 0, "tid": 103, "args": {"name": "SM 103"}}, {"name": "thread_sort_index", "ph": "M", "pid": 0, "tid": 103, "args": {"sort_index": 103}}, {"name": "thread_name", "ph": "M", "pid": 0, "tid": 104, "args": {"name": "SM 104"}}, {"name": "thread_sort_index", "ph": "M", "pid": 0, "tid": 104, "args": {"sort_index": 104}}, {"name": "thread_name", "ph": "M", "pid": 0, "tid": 105, "args": {"name": "SM 105"}}, {"name": "thread_sort_index", "ph": "M", "pid": 0, "tid": 105, "args": {"sort_index": 105}}, {"name": "thread_name", "ph": "M", "pid": 0, "tid": 106, "args": {"name": "SM 106"}}, {"name": "thread_sort_index", "ph": "M", "pid": 0, "tid": 106, "args": {"sort_index": 106}}, {"name": "thread_name", "ph": "M", "pid": 0, "tid": 107, "args": {"name": "SM 107"}}, {"name": "thread_sort_index", "ph": "M", "pid": 0, "tid": 107, "args": {"sort_index": 107}}, {"name": "thread_name", "ph": "M", "pid": 0, "tid": 108, "args": {"name": "SM 108"}}, {"name": "thread_sort_index", "ph": "M", "pid": 0, "tid": 108, "args": {"sort_index": 108}}, {"name": "thread_name", "ph": "M", "pid": 0, "tid": 109, "args": {"name": "SM 109"}}, {"name": "thread_sort_index", "ph": "M", "pid": 0, "tid": 109, "args": {"sort_index": 109}}, {"name": "thread_name", "ph": "M", "pid": 0, "tid": 110, "args": {"name": "SM 110"}}, {"name": "thread_sort_index", "ph": "M", "pid": 0, "tid": 110, "args": {"sort_index": 110}}, {"name": "thread_name", "ph": "M", "pid": 0, "tid": 111, "args": {"name": "SM 111"}}, {"name": "thread_sort_index", "ph": "M", "pid": 0, "tid": 111, "args": {"sort_index": 111}}, {"name": "thread_name", "ph": "M", "pid": 0, "tid": 112, "args": {"name": "SM 112"}}, {"name": "thread_sort_index", "ph": "M", "pid": 0, "tid": 112, "args": {"sort_index": 112}}, {"name": "thread_name", "ph": "M", "pid": 0, "tid": 113, "args": {"name": "SM 113"}}, {"name": "thread_sort_index", "ph": "M", "pid": 0, "tid": 113, "args": {"sort_index": 113}}, {"name": "thread_name", "ph": "M", "pid": 0, "tid": 114, "args": {"name": "SM 114"}}, {"name": "thread_sort_index", "ph": "M", "pid": 0, "tid": 114, "args": {"sort_index": 114}}, {"name": "thread_name", "ph": "M", "pid": 0, "tid": 115, "args": {"name": "SM 115"}}, {"name": "thread_sort_index", "ph": "M", "pid": 0, "tid": 115, "args": {"sort_index": 115}}, {"name": "thread_name", "ph": "M", "pid": 0, "tid": 116, "args": {"name": "SM 116"}}, {"name": "thread_sort_index", "ph": "M", "pid": 0, "tid": 116, "args": {"sort_index": 116}}, {"name": "thread_name", "ph": "M", "pid": 0, "tid": 117, "args": {"name": "SM 117"}}, {"name": "thread_sort_index", "ph": "M", "pid": 0, "tid": 117, "args": {"sort_index": 117}}, {"name": "thread_name", "ph": "M", "pid": 0, "tid": 118, "args": {"name": "SM 118"}}, {"name": "thread_sort_index", "ph": "M", "pid": 0, "tid": 118, "args": {"sort_index": 118}}, {"name": "thread_name", "ph": "M", "pid": 0, "tid": 119, "args": {"name": "SM 119"}}, {"name": "thread_sort_index", "ph": "M", "pid": 0, "tid": 119, "args": {"sort_index": 119}}, {"name": "thread_name", "ph": "M", "pid": 0, "tid": 120, "args": {"name": "SM 120"}}, {"name": "thread_sort_index", "ph": "M", "pid": 0, "tid": 120, "args": {"sort_index": 120}}, {"name": "thread_name", "ph": "M", "pid": 0, "tid": 121, "args": {"name": "SM 121"}}, {"name": "thread_sort_index", "ph": "M", "pid": 0, "tid": 121, "args": {"sort_index": 121}}, {"name": "thread_name", "ph": "M", "pid": 0, "tid": 122, "args": {"name": "SM 122"}}, {"name": "thread_sort_index", "ph": "M", "pid": 0, "tid": 122, "args": {"sort_index": 122}}, {"name": "thread_name", "ph": "M", "pid": 0, "tid": 123, "args": {"name": "SM 123"}}, {"name": "thread_sort_index", "ph": "M", "pid": 0, "tid": 123, "args": {"sort_index": 123}}, {"name": "thread_name", "ph": "M", "pid": 0, "tid": 124, "args": {"name": "SM 124"}}, {"name": "thread_sort_index", "ph": "M", "pid": 0, "tid": 124, "args": {"sort_index": 124}}, {"name": "thread_name", "ph": "M", "pid": 0, "tid": 125, "args": {"name": "SM 125"}}, {"name": "thread_sort_index", "ph": "M", "pid": 0, "tid": 125, "args": {"sort_index": 125}}, {"name": "thread_name", "ph": "M", "pid": 0, "tid": 126, "args": {"name": "SM 126"}}, {"name": "thread_sort_index", "ph": "M", "pid": 0, "tid": 126, "args": {"sort_index": 126}}, {"name": "thread_name", "ph": "M", "pid": 0, "tid": 127, "args": {"name": "SM 127"}}, {"name": "thread_sort_index", "ph": "M", "pid": 0, "tid": 127, "args": {"sort_index": 127}}, {"name": "thread_name", "ph": "M", "pid": 0, "tid": 128, "args": {"name": "SM 128"}}, {"name": "thread_sort_index", "ph": "M", "pid": 0, "tid": 128, "args": {"sort_index": 128}}, {"name": "thread_name", "ph": "M", "pid": 0, "tid": 129, "args": {"name": "SM 129"}}, {"name": "thread_sort_index", "ph": "M", "pid": 0, "tid": 129, "args": {"sort_index": 129}}, {"name": "thread_name", "ph": "M", "pid": 0, "tid": 130, "args": {"name": "SM 130"}}, {"name": "thread_sort_index", "ph": "M", "pid": 0, "tid": 130, "args": {"sort_index": 130}}, {"name": "thread_name", "ph": "M", "pid": 0, "tid": 131, "args": {"name": "SM 131"}}, {"name": "thread_sort_index", "ph": "M", "pid": 0, "tid": 131, "args": {"sort_index": 131}}, {"name": "thread_name", "ph": "M", "pid": 0, "tid": 132, "args": {"name": "SM 132"}}, {"name": "thread_sort_index", "ph": "M", "pid": 0, "tid": 132, "args": {"sort_index": 132}}, {"name": "thread_name", "ph": "M", "pid": 0, "tid": 133, "args": {"name": "SM 133"}}, {"name": "thread_sort_index", "ph": "M", "pid": 0, "tid": 133, "args": {"sort_index": 133}}, {"name": "thread_name", "ph": "M", "pid": 0, "tid": 134, "args": {"name": "SM 134"}}, {"name": "thread_sort_index", "ph": "M", "pid": 0, "tid": 134, "args": {"sort_index": 134}}, {"name": "thread_name", "ph": "M", "pid": 0, "tid": 135, "args": {"name": "SM 135"}}, {"name": "thread_sort_index", "ph": "M", "pid": 0, "tid": 135, "args": {"sort_index": 135}}, {"name": "thread_name", "ph": "M", "pid": 0, "tid": 136, "args": {"name": "SM 136"}}, {"name": "thread_sort_index", "ph": "M", "pid": 0, "tid": 136, "args": {"sort_index": 136}}, {"name": "thread_name", "ph": "M", "pid": 0, "tid": 137, "args": {"name": "SM 137"}}, {"name": "thread_sort_index", "ph": "M", "pid": 0, "tid": 137, "args": {"sort_index": 137}}, {"name": "thread_name", "ph": "M", "pid": 0, "tid": 138, "args": {"name": "SM 138"}}, {"name": "thread_sort_index", "ph": "M", "pid": 0, "tid": 138, "args": {"sort_index": 138}}, {"name": "thread_name", "ph": "M", "pid": 0, "tid": 139, "args": {"name": "SM 139"}}, {"name": "thread_sort_index", "ph": "M", "pid": 0, "tid": 139, "args": {"sort_index": 139}}, {"name": "thread_name", "ph": "M", "pid": 0, "tid": 140, "args": {"name": "SM 140"}}, {"name": "thread_sort_index", "ph": "M", "pid": 0, "tid": 140, "args": {"sort_index": 140}}, {"name": "thread_name", "ph": "M", "pid": 0, "tid": 141, "args": {"name": "SM 141"}}, {"name": "thread_sort_index", "ph": "M", "pid": 0, "tid": 141, "args": {"sort_index": 141}}, {"name": "thread_name", "ph": "M", "pid": 0, "tid": 142, "args": {"name": "SM 142"}}, {"name": "thread_sort_index", "ph": "M", "pid": 0, "tid": 142, "args": {"sort_index": 142}}, {"name": "thread_name", "ph": "M", "pid": 0, "tid": 143, "args": {"name": "SM 143"}}, {"name": "thread_sort_index", "ph": "M", "pid": 0, "tid": 143, "args": {"sort_index": 143}}, {"name": "thread_name", "ph": "M", "pid": 0, "tid": 144, "args": {"name": "SM 144"}}, {"name": "thread_sort_index", "ph": "M", "pid": 0, "tid": 144, "args": {"sort_index": 144}}, {"name": "thread_name", "ph": "M", "pid": 0, "tid": 145, "args": {"name": "SM 145"}}, {"name": "thread_sort_index", "ph": "M", "pid": 0, "tid": 145, "args": {"sort_index": 145}}, {"name": "thread_name", "ph": "M", "pid": 0, "tid": 146, "args": {"name": "SM 146"}}, {"name": "thread_sort_index", "ph": "M", "pid": 0, "tid": 146, "args": {"sort_index": 146}}, {"name": "thread_name", "ph": "M", "pid": 0, "tid": 147, "args": {"name": "SM 147"}}, {"name": "thread_sort_index", "ph": "M", "pid": 0, "tid": 147, "args": {"sort_index": 147}}], "displayTimeUnit": "ns"}